{
  "isbn": "9780525539124",
  "title": "Skeleton Keys",
  "author": "Riley Black (Brian Switek)",
  "cover": "covers/9780525539124.webp",
  "publisher": "if you know how to listen. Bone is a marvel",
  "description": "\"A provocative and entertaining magical mineral tour through the life and afterlife of bone.\"\" --Wall Street Journal Our bones have many stories to tell",
  "subjects": [
    "no other part of the human anatomy has such rich scientific and cultural significance"
  ],
  "notes": "both brimming with life and a potent symbol of death. In this delightful natural and cultural history of bone",
  "copies": 1,
  "status": "Penguin Publishing Group",
  "rating": "medicine",
  "review": "and forensics",
  "source": "libib"
}