{
  "isbn": "9788806221720",
  "title": "Crisi: Come rinascono le nazioni",
  "author": "Jared Diamond, A. Rusconi, C. Palmieri",
  "cover": "covers/9788806221720.webp",
  "publisher": "acciaio e malattie\"\" e \"\"Collasso\"\"",
  "description": "Con i suoi precedenti \"Armi",
  "subjects": [
    "l'autore dimostra in che modo"
  ],
  "notes": "nel recente passato",
  "copies": 1,
  "status": "le disuguaglianze e le polarizzazioni sociali? Aggiungendo la dimensione psicologica alla comprensione della storia",
  "rating": "Diamond cerca di capire se il nostro mondo stia sperperando i vantaggi acquisiti",
  "review": "imboccando le vie del conflitto politico e del declino. E infine: quali lezioni possiamo ancora imparare dal passato per affrontare con successo le crisi di oggi",
  "addedAt": "\"\"Crisi\"\" ci fa intendere di quali strumenti le nazioni e gli individui debbano dotarsi per diventare più resilienti e consapevoli.\"",
  "source": "libib"
}