{
  "isbn": "9788851171308",
  "title": "L' ultimo orizzonte. Cosa sappiamo dell'universo",
  "author": "Amedeo Balbi",
  "year": 2019,
  "cover": "covers/9788851171308.webp",
  "publisher": "UTET",
  "pages": 220,
  "description": "Cosa sappiamo dell'universo? Molto, moltissimo: la sua età, la sua struttura, cosa contiene e come ha fatto a evolvere in uno spazio disseminato di galassie, stelle, pianeti. Solo poco più di un secolo fa, non sapevamo quasi nulla di tutto questo. Il racconto di come la fisica moderna sia arrivata così avanti sulla strada della conoscenza del cosmo è il racconto di una straordinaria avventura scientifica, che Amedeo Balbi, astrofisico e divulgatore, ci aiuta a seguire passo dopo passo: dalla teoria della relatività di Einstein alla scoperta dell'espansione dell'universo, dall'osservazione della radiazione cosmica di fondo fino all'elaborazione del modello \"classico\" del Big Bang che oggi riteniamo la migliore descrizione dell'origine del cosmo. Allora, ormai sappiamo tutto dell'universo? Naturalmente no: se siamo sicuri dell'impianto generale, non abbiamo di certo definito con precisione tutti i dettagli. Balbi allora ci invita alla scoperta della terra di frontiera su cui si svolge la ricerca attuale, dalle conferme della teoria inflazionaria alla ricerca della materia oscura, alla spiegazione dell'accelerazione dell'espansione dell'universo. Ma anche alla frontiera della ricerca, siamo ben lontani dal trovare la risposta definitiva a domande basilari: l'universo è finito o infinito? Lo spazio e il tempo hanno avuto un inizio, e avranno una fine? Le leggi di natura potevano essere diverse? Esistono altri universi oltre il nostro? Per affrontare queste domande con gli strumenti della scienza bisogna spingersi oltre l'ultimo orizzonte, dove gli avvenimenti dei primordi sono nascosti al nostro sguardo da un muro di fuoco, dove le misurazioni che abbiamo fatto sull'universo potrebbero non valere più, dove potremmo scoprire che la fisica che abbiamo elaborato descrive solo un breve momento e un limitato spazio di un ben più ampio e irraggiungibile cosmo. Cosa sappiamo dell'universo?",
  "subjects": [],
  "addedAt": "2019-09-20",
}