{
  "isbn": "9788854517615",
  "title": "Fratelli d'anima",
  "author": "David Diop, G. Bogliolo",
  "year": 2019,
  "cover": "covers/9788854517615.webp",
  "publisher": "Neri Pozza",
  "pages": 122,
  "description": "Sul fronte occidentale, nelle trincee francesi, tra i soldati bianchi coi loro vistosi calzoni rossi spiccano i fucilieri senegalesi, «i cioccolatini dell'Africa nera», come li chiama il capitano Armand. Prima di ogni assalto, il capitano non manca di ricordare loro che sono l'orgoglio della Francia, «i più coraggiosi dei coraggiosi», un autentico incubo per i nemici che hanno paura dei «negri selvaggi, dei cannibali, degli zulù». I senegalesi ridono contenti. Poi, mettendosi in faccia gli occhi da matto, sbucano ,fuori dalla trincea con il fucile nella mano sinistra e il machete nella destra. Alfa Ndiaye e Mademba Diop sono amici, fratelli d'anima cresciuti insieme in Africa, lontano dai freddi accampamenti del fronte. Quando in trincea risuona il colpo di fischietto del capitano, escono anche loro dal buco urlando come selvaggi indemoniati per non apparire meno coraggiosi degli altri. Un giorno, però, Mademba Diop viene ferito mortalmente e, con le budella all'aria, chiede per tre volte ad Alfa di dargli il colpo di grazia. Per tre volte Alfa si rifiuta e, dopo una lunga e atroce agonia, Mademba muore. La morte dell'amico consegna Alfa all'impensabile, a tutto ciò che gli antenati e il mondo di ieri avrebbero proibito e che invece la grande carneficina della guerra moderna concede. A ogni fischio di chiamata del capitano Armand, Alfa si precipita fuori dalla trincea e corre verso i «nemici dagli occhi azzurri», uccidendo senza pietà e tagliando alle sue vittime una mano come trofeo di guerra. Una, due, tre, quattro... otto mani. Come un demone, uno stregone, un divoratore di anime, che soltanto una voce del mondo di ieri potrebbe salvare...Un romanzo che mostra come nel naufragio totale della civiltà rappresentato dalla Grande Guerra non soltanto l'Europa, ma anche una parte non trascurabile dell'Africa perse la sua anima e la millenaria tradizione che la custodiva.",
  "subjects": [],
  "copies": 1,
  "addedAt": "2019-09-23",
  "source": "libib"
}