{
  "isbn": "9788845938290",
  "title": "Kabloona. L'uomo bianco",
  "author": "Gontran de Poncins",
  "year": 2023,
  "cover": "covers/9788845938290.webp",
  "publisher": "Adelphi",
  "pages": 332,
  "description": "Nel 1938 un visconte francese avventuroso e un po’ avventuriero, sempre alla ricerca di un senso da dare alla vita, decide di partire per l’estremo Nord, al di là del Canada, dove vivono le popolazioni più «primitive». Nel racconto di questa esperienza – una lenta e progressiva acclimatazione, in ogni senso, al nuovo mondo – tutto incanta fin dal primo istante: le durissime prove di resistenza, l’asprezza degli elementi, descritti con una vivacità e un’immediatezza fuori del comune, ma sopra ogni altra cosa l’incontro con gli Inuit, i più arcaici abitanti dell’Artico. Dapprima irrigidito nella sua supremazia di Kabloona, «uomo bianco» – si spingerà a dire che gli Inuit «non pensano», il che secondo i nostri angusti canoni potrebbe sembrare vero –, Gontran de Poncins finirà per imparare molto da queste genti, che non si pongono affatto il problema di dare un senso alla vita, come scopriremo in pagine profonde, spiazzanti, educative nel senso più alto della parola. E nell’ora sofferta del ritorno, si renderà conto, inaspettatamente, di essere diventato uno di loro. Il suo cuore rimarrà lì, come quello di noi lettori, illuminati da un’avventura che, superando ogni distanza, riesce a farci entrare nell’anima di un popolo e di un tempo che non potranno essere più. Disegni e fotografie dell’Autore. Leggi di più",
  "subjects": [],
  "copies": 1,
  "addedAt": "2025-11-25",
  "source": "libib"
}