{
  "isbn": "9788832850147",
  "title": "Filosofia del futuro. Un'introduzione",
  "author": "Samuele Iaquinto, Giuliano Torrengo",
  "year": 2018,
  "cover": "covers/9788832850147.webp",
  "publisher": "Cortina Raffaello",
  "pages": 171,
  "description": "Il volume offre un'introduzione al contempo accessibile e rigorosa ai più recenti sviluppi di una fondamentale branca della filosofia del tempo: la filosofia del futuro. Al centro dell'attenzione sono le domande chiave del dibattito contemporaneo. Il futuro è già scritto o esistono cammini alternativi che il tempo è in grado di imboccare? Esistere significa semplicemente essere presenti o ci sono veri e propri oggetti futuri? Siamo davvero liberi di scegliere quali azioni compiere e di modificare il corso degli eventi? Il dibattito intorno alle risposte di volta in volta offerte dalla filosofia esplora un'intrigante zona d'intersezione tra metafisica, logica ed etica, e interessa discipline diverse come la fisica, la psicologia e l'economia. Gli autori offrono gli strumenti necessari per inquadrare concettualmente le domande sul futuro, introducendo tutte le nozioni tecniche in un linguaggio chiaro e intuitivo.",
  "subjects": [],
  "addedAt": "2018-12-25",
}