{
  "isbn": "9788899270049",
  "title": "Viva l'Italia",
  "author": "Roberta Cairoli",
  "year": 2015,
  "cover": "covers/9788899270049.webp",
  "publisher": "Enciclopedia delle Donne",
  "pages": 190,
  "description": "Realizzato in collaborazione con la FIAP, Viva l’Italia è uno strumento didattico per i ragazzi e le scuole che vogliano approfondire il tema dell’antifascismo italiano.\nAttraverso il racconto biografico di 65 donne e uomini offre alle giovani generazioni una testimonianza viva e concreta della pluralità dei modi in cui queste persone hanno voluto e potuto, in situazioni diverse, esprimere la loro scelta di libertà, combattendo il fascismo e contribuendo poi a costruire un sistema sociale più giusto.\nIl volume, a cura di Federica Artali e Roberta Cairoli, è ricco di illustrazioni originali, di Lorenzo Gritti, ed è corredato da una sezione didattica appositamente realizzata Con giochi e lavori di gruppo, pensati per le scuole secondarie di primo grado ma adattabili a contesti ed età differenti.",
  "subjects": [],
  "copies": 1,
  "addedAt": "2022-06-28",
  "source": "libib"
}