{
  "isbn": "9788836005765",
  "title": "La Divina Commedia",
  "author": "Dante Alighieri, G. Vandelli, L. Polacco",
  "year": 2021,
  "cover": "covers/9788836005765.webp",
  "publisher": "Hoepli",
  "pages": 624,
  "description": "Ristampa anastatica del celebre “Dante minuscolo Hoepliano” in tre volumi, uno per cantica, in brossura, raccolti in un apposito astuccio. Pubblicata per la prima volta nel 1904, questa edizione del testo dantesco è arricchita dalle postille e cenni introduttivi del prof. Raffaello Fornaciari, riveduti dal prof. Piero Scazzoso e dalle decorazioni di Ezio Anichini che impreziosiscono copertine e astuccio. Una proposta che rielabora la versione minuscola hoepliana della Divina Commedia presentando ciascuna delle tre cantiche come un volume a sé stante, così da poter ancor più agevolmente maneggiare l’elevato e al tempo stesso diverso contenuto poetico e dottrinale dell’Inferno, del Purgatorio e del Paradiso. Leggi di più Leggi meno",
  "subjects": [],
  "copies": 1,
  "addedAt": "2005-09-20",
  "source": "libib"
}